fine_python_ast/__init__.py
fine_python_ast/ast_provider.py
fine_python_ast/iast_provider.py
fine_python_ast/py.typed
fine_python_ast-0.2.0.dist-info/METADATA
fine_python_ast-0.2.0.dist-info/WHEEL
fine_python_ast-0.2.0.dist-info/top_level.txt
fine_python_ast-0.2.0.dist-info/RECORD
