Metadata-Version: 2.4
Name: fine-python-ast
Version: 0.2.0
Author-email: Vladyslav Hnatiuk <aders1234@gmail.com>
Requires-Python: <3.14,>=3.11
Requires-Dist: finecode_extension_api==0.3.*
